{
    "package-id": "hl7.fhir.us.cimi-labs",
    "title": "Base Laboratory Class FHIR Profiles",
    "canonical": "http://hl7.org/fhir/us/cimi-labs",
    "introduction": "Logical, abstract laboratory profiles created and maintained by the CIMI working group and sponsored by the OO working group.",
    "list": [{
            "version": "current",
            "desc": "Continuous Integration Build (latest in version control)",
            "path": "http://hl7.org/fhir/us/cimi-labs",
            "status": "ci-build",
            "current": true
        }
    ]
}