<?xml version="1.0" encoding="UTF-8"?>
<StructureDefinition xmlns="http://hl7.org/fhir">
    <!--© 2018 IHC Health Services, Inc. All Rights Reserved. This document is machine generated.-->
    <id value="BlatellagermanicaAbIgGACncPtSerQnLabObs"/>
    <url value="http://hl7.org/fhir/hspc/StructureDefinition/BlatellagermanicaAbIgGACncPtSerQnLabObs"/>
    <name value="HSPC Blatellagermanica Ab Ig GA Cnc Pt Ser Qn Lab"/>
    <status value="draft"/>
    <date value="2010-07-03"/>
    <publisher value="Healthcare Services Platform Consortium"/>
    <description value="BlatellagermanicaAbIgGACncPtSerQnLabObs is a Clinical Element Model for LOINC Code: 24139-8 LOINC Name: BlatellagermanicaAb.IgG:ACnc:Pt:Ser:Qn"/>
    <fhirVersion value="4.0.0"/>
    <kind value="complex-type"/>
    <abstract value="false"/>
    <type value="Observation"/>
    <baseDefinition value="http://hl7.org/fhir/us/core/StructureDefinition/us-core-observation-lab"/>
    <derivation value="constraint"/>
    <differential>
        <element id="Observation:hspcBlatellagermanicaAbIgGACncPtSerQnLabObs">
            <path value="Observation"/>
            <definition value="BlatellagermanicaAbIgGACncPtSerQnLabObs is a Clinical Element Model for LOINC Code: 24139-8 LOINC Name: BlatellagermanicaAb.IgG:ACnc:Pt:Ser:Qn"/>
        </element>
        <element id="Observation:hspcBlatellagermanicaAbIgGACncPtSerQnLabObs.key">
            <path value="Observation.code"/>
            <short value="Observation:hspcBlatellagermanicaAbIgGACncPtSerQnLabObs.key"/>
            <fixedCodeableConcept>
                <coding>
                    <system value="http://loinc.org"/>
                    <code value="24139-8"/>
                    <display value="Cockroach IgG Ab [Units/volume] in Serum"/>
                </coding>
            </fixedCodeableConcept>
        </element>
        <element id="Observation:hspcBlatellagermanicaAbIgGACncPtSerQnLabObs.valueQuantity">
            <path value="Observation.valueQuantity"/>
            <short value="Observation:hspcBlatellagermanicaAbIgGACncPtSerQnLabObs.valueQuantity"/>
            <type>
                <code value="Quantity"/>
            </type>
        </element>
        <element id="Observation:hspcBlatellagermanicaAbIgGACncPtSerQnLabObs.interpretation">
            <path value="Observation.interpretation"/>
            <short value="Observation:hspcBlatellagermanicaAbIgGACncPtSerQnLabObs.interpretation"/>
            <comment value="Key code for this model: Interpretation_KEY_CODE"/>
            <min value="0"/>
            <max value="1"/>
            <type>
                <code value="CodeableConcept"/>
            </type>
        </element>
        <element id="Observation:hspcBlatellagermanicaAbIgGACncPtSerQnLabObs.resultedDateTime">
            <path value="Observation.issued"/>
            <short value="Observation:hspcBlatellagermanicaAbIgGACncPtSerQnLabObs.resultedDateTime"/>
            <comment value="Key code for this model: ResultedDateTime_KEY_CODE"/>
            <min value="0"/>
            <max value="1"/>
            <type>
                <code value="instant"/>
            </type>
        </element>
        <element id="Observation:hspcBlatellagermanicaAbIgGACncPtSerQnLabObs.modifierExtension:focalSubject">
            <path value="Observation.modifierExtension"/>
            <short value="Observation:hspcBlatellagermanicaAbIgGACncPtSerQnLabObs.modifierExtension:focalSubject"/>
            <comment value="Key code for this model: FocalSubject_KEY_CODE"/>
            <min value="0"/>
            <max value="1"/>
            <type>
                <code value="modifierExtension"/>
                <profile value="http://hl7.org/fhir/hspc/StructureDefinition/focalSubject"/>
            </type>
        </element>
        <element id="Observation:hspcBlatellagermanicaAbIgGACncPtSerQnLabObs.referenceRangeNar">
            <path value="Observation.referenceRange.text"/>
            <short value="Observation:hspcBlatellagermanicaAbIgGACncPtSerQnLabObs.referenceRangeNar"/>
            <comment value="Key code for this model: ReferenceRangeNar_KEY_CODE"/>
            <min value="0"/>
            <max value="1"/>
            <type>
                <code value="string"/>
            </type>
        </element>
        <element id="Observation:hspcBlatellagermanicaAbIgGACncPtSerQnLabObs:identifier">
            <path value="Observation.identifier"/>
            <slicing>
                <discriminator>
                    <type value="value"/>
                    <path value="Observation.identifier"/>
                </discriminator>
                <ordered value="false"/>
                <rules value="open"/>
            </slicing>
            <min value="0"/>
            <max value="*"/>
        </element>
        <element id="Observation:hspcBlatellagermanicaAbIgGACncPtSerQnLabObs:accessionNumber">
            <path value="Observation.identifier"/>
            <sliceName value="accessionnumber"/>
            <short value="Observation:hspcBlatellagermanicaAbIgGACncPtSerQnLabObs:accessionNumber"/>
            <comment value="Key code for this model: AccessionNumber_KEY_CODE"/>
            <min value="0"/>
            <max value="1"/>
            <type>
                <code value="Identifier"/>
            </type>
        </element>
        <element id="Observation:hspcBlatellagermanicaAbIgGACncPtSerQnLabObs:fillerOrderNumber">
            <path value="Observation.identifier"/>
            <sliceName value="fillerordernumber"/>
            <short value="Observation:hspcBlatellagermanicaAbIgGACncPtSerQnLabObs:fillerOrderNumber"/>
            <comment value="Key code for this model: FillerOrderNumber_KEY_CODE"/>
            <min value="0"/>
            <max value="1"/>
            <type>
                <code value="Identifier"/>
            </type>
        </element>
        <element id="Observation:hspcBlatellagermanicaAbIgGACncPtSerQnLabObs:placerOrderNumber">
            <path value="Observation.identifier"/>
            <sliceName value="placerordernumber"/>
            <short value="Observation:hspcBlatellagermanicaAbIgGACncPtSerQnLabObs:placerOrderNumber"/>
            <comment value="Key code for this model: PlacerOrderNumber_KEY_CODE"/>
            <min value="0"/>
            <max value="1"/>
            <type>
                <code value="Identifier"/>
            </type>
        </element>
        <element id="Observation:hspcBlatellagermanicaAbIgGACncPtSerQnLabObs:performer">
            <path value="Observation.performer"/>
            <slicing>
                <discriminator>
                    <type value="value"/>
                    <path value="Observation.performer"/>
                </discriminator>
                <ordered value="false"/>
                <rules value="open"/>
            </slicing>
            <min value="0"/>
            <max value="*"/>
        </element>
        <element id="Observation:hspcBlatellagermanicaAbIgGACncPtSerQnLabObs:responsibleObserver">
            <path value="Observation.performer"/>
            <sliceName value="responsibleobserver"/>
            <short value="Observation:hspcBlatellagermanicaAbIgGACncPtSerQnLabObs:responsibleObserver"/>
            <comment value="Key code for this model: ResponsibleObserver_KEY_CODE"/>
            <min value="0"/>
            <max value="*"/>
            <type>
                <code value="Reference"/>
                <targetProfile value="http://hl7.org/fhir/hspc/StructureDefinition/practitioner"/>
            </type>
        </element>
        <element id="Observation:hspcBlatellagermanicaAbIgGACncPtSerQnLabObs:performingLaboratory">
            <path value="Observation.performer"/>
            <sliceName value="performinglaboratory"/>
            <short value="Observation:hspcBlatellagermanicaAbIgGACncPtSerQnLabObs:performingLaboratory"/>
            <comment value="Key code for this model: PerformingLaboratory_KEY_CODE"/>
            <min value="0"/>
            <max value="1"/>
            <type>
                <code value="Reference"/>
                <targetProfile value="http://hl7.org/fhir/hspc/StructureDefinition/organization"/>
            </type>
        </element>
        <element id="Observation:hspcBlatellagermanicaAbIgGACncPtSerQnLabObs:performingOrganizationMedicalDirector">
            <path value="Observation.performer"/>
            <sliceName value="performingorganizationmedicaldirector"/>
            <short value="Observation:hspcBlatellagermanicaAbIgGACncPtSerQnLabObs:performingOrganizationMedicalDirector"/>
            <comment value="Key code for this model: PerformingOrganizationMedicalDirector_KEY_CODE"/>
            <min value="0"/>
            <max value="1"/>
            <type>
                <code value="Reference"/>
                <targetProfile value="http://hl7.org/fhir/hspc/StructureDefinition/practitioner"/>
            </type>
        </element>
        <element id="Observation:hspcBlatellagermanicaAbIgGACncPtSerQnLabObs:extension">
            <path value="Observation.extension"/>
            <slicing>
                <discriminator>
                    <type value="value"/>
                    <path value="Observation.extension"/>
                </discriminator>
                <ordered value="false"/>
                <rules value="open"/>
            </slicing>
            <min value="0"/>
            <max value="*"/>
        </element>
        <element id="Observation:hspcBlatellagermanicaAbIgGACncPtSerQnLabObs:reportingPriority">
            <path value="Observation.extension"/>
            <sliceName value="reportingpriority"/>
            <short value="Observation:hspcBlatellagermanicaAbIgGACncPtSerQnLabObs:reportingPriority"/>
            <comment value="Key code for this model: ReportingPriority_KEY_CODE"/>
            <min value="0"/>
            <max value="1"/>
            <type>
                <code value="extension"/>
                <profile value="http://hl7.org/fhir/hspc/StructureDefinition/reportingPriority"/>
            </type>
        </element>
        <element id="Observation:hspcBlatellagermanicaAbIgGACncPtSerQnLabObs:deltaFlag">
            <path value="Observation.extension"/>
            <sliceName value="deltaflag"/>
            <short value="Observation:hspcBlatellagermanicaAbIgGACncPtSerQnLabObs:deltaFlag"/>
            <comment value="Key code for this model: DeltaFlag_KEY_CODE"/>
            <min value="0"/>
            <max value="1"/>
            <type>
                <code value="extension"/>
                <profile value="http://hl7.org/fhir/hspc/StructureDefinition/deltaFlag"/>
            </type>
        </element>
    </differential>
</StructureDefinition>
